fuzzy_couscous/__init__.py
fuzzy_couscous/commands/__init__.py
fuzzy_couscous/commands/htmx.py
fuzzy_couscous/commands/make.py
fuzzy_couscous/commands/remove_poetry/__init__.py
fuzzy_couscous/commands/remove_poetry/config_converters.py
fuzzy_couscous/commands/remove_poetry/utils.py
fuzzy_couscous/commands/remove_poetry/virtualenv_.py
fuzzy_couscous/commands/rm_migrations.py
fuzzy_couscous/commands/work.py
fuzzy_couscous/commands/write_env.py
fuzzy_couscous/config.py
fuzzy_couscous/main.py
fuzzy_couscous/utils.py
fuzzy_couscous-3.1.3.dist-info/LICENSE
fuzzy_couscous-3.1.3.dist-info/METADATA
fuzzy_couscous-3.1.3.dist-info/WHEEL
fuzzy_couscous-3.1.3.dist-info/entry_points.txt
fuzzy_couscous-3.1.3.dist-info/RECORD
