Metadata-Version: 2.1
Name: fuzzy-couscous
Version: 3.1.3
Summary: A cli tool to bootstrap your django projects and enhance your development experience.
Home-page: https://tobi-de.github.io/fuzzy-couscous/
License: MIT
Keywords: django,python,cookiecutter,project-template
Author: Tobi-De
Author-email: tobidegnon@proton.me
Requires-Python: >=3.10,<4.0
Classifier: Development Status :: 5 - Production/Stable
Classifier: Framework :: Django :: 4
Classifier: Framework :: Django :: 4.0
Classifier: Framework :: Django :: 4.1
Classifier: Intended Audience :: Developers
Classifier: License :: OSI Approved :: MIT License
Classifier: Natural Language :: English
Classifier: Programming Language :: Python
Classifier: Programming Language :: Python :: 3
Classifier: Programming Language :: Python :: 3.10
Classifier: Programming Language :: Python :: 3.11
Classifier: Programming Language :: Python :: 3.12
Classifier: Programming Language :: Python :: Implementation :: CPython
Classifier: Programming Language :: Python :: Implementation :: PyPy
Requires-Dist: dict-deep (>=4.1.2,<5.0.0)
Requires-Dist: django (>=4.2.7,<5.0.0)
Requires-Dist: honcho (>=1.1.0,<2.0.0)
Requires-Dist: httpx (>=0.25.1,<0.26.0)
Requires-Dist: hupper (>=1.12,<2.0)
Requires-Dist: python-dotenv (>=1.0.0,<2.0.0)
Requires-Dist: pyyaml (==6.0.1)
Requires-Dist: rich (>=13.7.0,<14.0.0)
Requires-Dist: tomli (>=2.0.1,<3.0.0) ; python_version < "3.11"
Requires-Dist: tomli-w (>=1.0.0,<2.0.0)
Requires-Dist: typer (>=0.9.0,<0.10.0)
Project-URL: Documentation, https://tobi-de.github.io/fuzzy-couscous
Project-URL: Repository, https://github.com/Tobi-De/fuzzy-couscous
